minesweeper_sandbox/__init__.py
minesweeper_sandbox/board.py
minesweeper_sandbox/cell.py
minesweeper_sandbox/game.py
minesweeper_sandbox/py.typed
minesweeper_sandbox-1.1.0.dist-info/LICENSE
minesweeper_sandbox-1.1.0.dist-info/METADATA
minesweeper_sandbox-1.1.0.dist-info/WHEEL
minesweeper_sandbox-1.1.0.dist-info/top_level.txt
minesweeper_sandbox-1.1.0.dist-info/RECORD
